ballotapi/__init__.py
ballotapi/cli.py
ballotapi/export.py
ballotapi/load.py
ballotapi/runserver.py
ballotapi-0.0.1.dist-info/LICENSE
ballotapi-0.0.1.dist-info/METADATA
ballotapi-0.0.1.dist-info/WHEEL
ballotapi-0.0.1.dist-info/entry_points.txt
ballotapi-0.0.1.dist-info/top_level.txt
ballotapi-0.0.1.dist-info/RECORD
