Metadata-Version: 2.1
Name: ballotapi
Version: 0.0.1
Summary: REST API server for U.S. election ballot information
Home-page: https://ballotapi.org
Author: Daniel Roesler
Author-email: diafygi@gmail.com
License: Public Domain
Project-URL: Code, https://github.com/open-austin/ballotapi
Project-URL: Issue tracker, https://github.com/open-austin/ballotapi/issues
Project-URL: Documentation, https://ballotapi.org/docs
Keywords: ballotapi,ballot api,election api
Platform: UNKNOWN
Classifier: Development Status :: 1 - Planning
Classifier: Environment :: Console
Classifier: Environment :: Web Environment
Classifier: Intended Audience :: Developers
Classifier: Intended Audience :: Education
Classifier: Intended Audience :: System Administrators
Classifier: License :: Public Domain
Classifier: Operating System :: OS Independent
Classifier: Programming Language :: Python
Classifier: Programming Language :: Python :: 2
Classifier: Programming Language :: Python :: 2.7
Classifier: Programming Language :: Python :: 3
Classifier: Programming Language :: Python :: 3.3
Classifier: Programming Language :: Python :: 3.4
Classifier: Programming Language :: Python :: 3.5
Classifier: Programming Language :: Python :: 3.6
Classifier: Programming Language :: Python :: 3.7
Requires-Python: >=2.7, !=3.0.*, !=3.1.*, !=3.2.*
Requires-Dist: uwsgi
Requires-Dist: psycopg2
Requires-Dist: redis
Requires-Dist: pyyaml
